README.md
setup.py
modeleval/__init__.py
modeleval/evaluation.py
modeleval.egg-info/PKG-INFO
modeleval.egg-info/SOURCES.txt
modeleval.egg-info/dependency_links.txt
modeleval.egg-info/not-zip-safe
modeleval.egg-info/requires.txt
modeleval.egg-info/top_level.txt